engramic/__about__.py
engramic/__init__.py
engramic/py.typed
engramic/application/__init__.py
engramic/application/codify/__init__.py
engramic/application/codify/codify_service.py
engramic/application/codify/prompt_validate_prompt.py
engramic/application/consolidate/__init__.py
engramic/application/consolidate/consolidate_service.py
engramic/application/consolidate/prompt_gen_indices.py
engramic/application/message/__init__.py
engramic/application/message/message_service.py
engramic/application/progress/__init__.py
engramic/application/progress/progress_service.py
engramic/application/repo/__init__.py
engramic/application/repo/repo_service.py
engramic/application/response/__init__.py
engramic/application/response/prompt_main_prompt.py
engramic/application/response/response_service.py
engramic/application/retrieve/__init__.py
engramic/application/retrieve/ask.py
engramic/application/retrieve/prompt_analyze_prompt.py
engramic/application/retrieve/prompt_gen_conversation.py
engramic/application/retrieve/prompt_gen_indices.py
engramic/application/retrieve/retrieve_service.py
engramic/application/sense/__init__.py
engramic/application/sense/prompt_gen_full_summary.py
engramic/application/sense/prompt_gen_meta.py
engramic/application/sense/prompt_scan_page.py
engramic/application/sense/scan.py
engramic/application/sense/sense_service.py
engramic/application/storage/__init__.py
engramic/application/storage/st
engramic/application/storage/storage_service.py
engramic/application/teach/__init__.py
engramic/application/teach/lesson.py
engramic/application/teach/prompt_gen_questions.py
engramic/application/teach/teach_service.py
engramic/core/__init__.py
engramic/core/document.py
engramic/core/engram.py
engramic/core/host.py
engramic/core/index.py
engramic/core/meta.py
engramic/core/metrics_tracker.py
engramic/core/observation.py
engramic/core/prompt.py
engramic/core/prompt_analysis.py
engramic/core/repo.py
engramic/core/response.py
engramic/core/retrieve_result.py
engramic-0.4.0.dist-info/METADATA
engramic-0.4.0.dist-info/WHEEL
engramic-0.4.0.dist-info/licenses/LICENSE.txt
engramic-0.4.0.dist-info/RECORD
