Metadata-Version: 2.4
Name: engramic
Version: 0.4.0
Summary: An open source (for companies less than 250 employees) AI library for processing, storing, and retrieving proprietary, unstructured data.
Project-URL: Documentation, https://github.com/engramic/engramic#readme
Project-URL: Issues, https://github.com/engramic/engramic/issues
Project-URL: Source, https://github.com/engramic/engramic
Author-email: "Preisz Consulting, LLC" <license@engramic.org>
License: Engramic Community License
License-File: LICENSE.txt
Keywords: AI,LLM,Memory,RAG,Retrieval Augmented Generation
Classifier: Development Status :: 4 - Beta
Classifier: Programming Language :: Python
Classifier: Programming Language :: Python :: 3.10
Classifier: Programming Language :: Python :: 3.11
Classifier: Programming Language :: Python :: 3.12
Classifier: Programming Language :: Python :: 3.13
Classifier: Programming Language :: Python :: Implementation :: CPython
Classifier: Programming Language :: Python :: Implementation :: PyPy
Requires-Python: >=3.10
Requires-Dist: cachetools<6.0,>=5.5.2
Requires-Dist: mako<2.0,>=1.3.0
Requires-Dist: pluggy<2.0,>=1.5
Requires-Dist: pyjwt<3.0,>=2.10.1
Requires-Dist: pymupdf<2.0,>=1.25
Requires-Dist: pyzmq<27.0,>=26.4.0
Requires-Dist: tomli<3.0,>=2.2.1
Requires-Dist: websockets<16.0,>=15.0.1
